xdot_rs-0.2.3.dist-info/METADATA
xdot_rs-0.2.3.dist-info/WHEEL
xdot_rs/__init__.py
xdot_rs/xdot_rs.cpython-38-x86_64-linux-gnu.so
xdot_rs-0.2.3.dist-info/RECORD
