Metadata-Version: 2.1
Name: xdot-rs
Version: 0.2.3
Classifier: License :: OSI Approved :: GNU General Public License v3 or later (GPLv3+)
Classifier: Development Status :: 4 - Beta
Classifier: Intended Audience :: Developers
Classifier: Programming Language :: Python :: 3
Requires-Dist: maturin ; extra == 'dev'
Requires-Dist: pre-commit ; extra == 'dev'
Requires-Dist: black ; extra == 'dev'
Requires-Dist: pytest ; extra == 'test'
Provides-Extra: dev
Provides-Extra: test
Summary: Parse graphviz’ xdot draw instructions
Keywords: graphviz,graph
Author: Philipp A. <flying-sheep@web.de>
Author-email: Philipp A. <flying-sheep@web.de>
License: GPL-3.0
Requires-Python: >= 3.8
Project-URL: Source, https://github.com/flying-sheep/xdot-rust
